mercat2-1.4.1.data/scripts/mercat2.py
mercat2_lib/__init__.py
mercat2_lib/mercat2_Chunker.py
mercat2_lib/mercat2_diversity.py
mercat2_lib/mercat2_fasta.py
mercat2_lib/mercat2_figures.py
mercat2_lib/mercat2_kmers.py
mercat2_lib/mercat2_metrics.py
mercat2_lib/mercat2_report.py
mercat2_lib/FGS/FragGeneScanRS-darwin.tar.gz
mercat2_lib/FGS/FragGeneScanRS-linux.tar.gz
mercat2_lib/__pycache__/__init__.cpython-37.pyc
mercat2_lib/__pycache__/mercat2_Chunker.cpython-37.pyc
mercat2_lib/__pycache__/mercat2_fasta.cpython-37.pyc
mercat2_lib/__pycache__/mercat2_kmers.cpython-37.pyc
mercat2_lib/__pycache__/mercat2_metrics.cpython-37.pyc
mercat2_lib/__pycache__/mercat2_qc.cpython-37.pyc
mercat2_lib/__pycache__/mercat2_report.cpython-37.pyc
mercat2_lib/data/adapter.fna
mercat2_lib/data/logo.jpg
mercat2_lib/data/style.css
mercat2-1.4.1.dist-info/LICENSE.txt
mercat2-1.4.1.dist-info/METADATA
mercat2-1.4.1.dist-info/WHEEL
mercat2-1.4.1.dist-info/top_level.txt
mercat2-1.4.1.dist-info/RECORD
