Metadata-Version: 2.1
Name: mercat2
Version: 1.4.1
Summary: versatile k-mer counter and diversity estimator for database independent property analysis (DIPA) for multi-omic analysis
Home-page: https://github.com/raw-lab/mercat2
Author: Jose L. Figueroa III, Richard A. White III
Author-email: jlfiguer@charlotte.edu
License: BSD License
Platform: Unix
Classifier: Programming Language :: Python :: 3
Classifier: Programming Language :: Python :: 3.9
Classifier: Programming Language :: Python :: 3.10
Classifier: License :: OSI Approved :: BSD License
Classifier: Operating System :: Unix
Requires-Python: >=3.9
License-File: LICENSE.txt
Requires-Dist: setuptools
Requires-Dist: grpcio ==1.43
Requires-Dist: ray
Requires-Dist: configargparse
Requires-Dist: pandas
Requires-Dist: numpy
Requires-Dist: humanize
Requires-Dist: plotly
Requires-Dist: psutil
Requires-Dist: dominate
Requires-Dist: scikit-learn
Requires-Dist: scikit-bio
Requires-Dist: scipy
Requires-Dist: metaomestats
Requires-Dist: kaleido
